erdb/__init__.py
erdb/__main__.py
erdb/py.typed
erdb/app_api/__init__.py
erdb/app_api/common.py
erdb/app_api/endpoints.py
erdb/app_api/main.py
erdb/app_wiki/__init__.py
erdb/data/contrib/Armament/Lance.json
erdb/data/contrib/Armor/Albinauric Mask.json
erdb/data/contrib/AshOfWar/Ash of War Lion's Claw.json
erdb/data/contrib/SpiritAsh/Black Knife Tiche.json
erdb/data/contrib/Talisman/Radagon's Soreseal.json
erdb/data/gamedata/1.02.1.zip
erdb/data/gamedata/1.02.2.zip
erdb/data/gamedata/1.02.3.zip
erdb/data/gamedata/1.03.1.zip
erdb/data/gamedata/1.03.2.zip
erdb/data/gamedata/1.03.3.zip
erdb/data/gamedata/1.04.1.zip
erdb/data/gamedata/1.04.2.zip
erdb/data/gamedata/1.05.0.zip
erdb/data/gamedata/1.06.0.zip
erdb/data/gamedata/1.07.0.zip
erdb/data/gamedata/1.07.1.zip
erdb/data/gamedata/1.08.0.zip
erdb/data/gamedata/1.08.1.zip
erdb/data/gamedata/1.09.0.zip
erdb/data/gamedata/1.10.0.zip
erdb/data/gamedata/manifest.json
erdb/data/thirdparty/README.md
erdb/data/wiki/scripts/ar_calculator.py
erdb/data/wiki/templates/ar-calculator.html.jinja
erdb/data/wiki/templates/armaments-index.html.jinja
erdb/data/wiki/templates/armaments-single.html.jinja
erdb/effect_parser/__init__.py
erdb/effect_parser/aggregator.py
erdb/effect_parser/attribute_fields.py
erdb/effect_parser/hardcoded.py
erdb/effect_parser/parsers.py
erdb/loaders/__init__.py
erdb/loaders/contrib.py
erdb/loaders/params.py
erdb/main/__init__.py
erdb/main/app.py
erdb/main/args.py
erdb/main/cli.py
erdb/shop/__init__.py
erdb/shop/shop_typing.py
erdb/table/__init__.py
erdb/table/_common.py
erdb/table/_retrievers.py
erdb/table/ammo.py
erdb/table/armaments.py
erdb/table/armor.py
erdb/table/ashes_of_war.py
erdb/table/bolstering_materials.py
erdb/table/correction_attack.py
erdb/table/correction_graph.py
erdb/table/crafting_materials.py
erdb/table/gestures.py
erdb/table/info.py
erdb/table/keys.py
erdb/table/reinforcements.py
erdb/table/shop.py
erdb/table/spells.py
erdb/table/spirit_ashes.py
erdb/table/talismans.py
erdb/table/tools.py
erdb-0.4.0.dist-info/entry_points.txt
erdb-0.4.0.dist-info/LICENSE
erdb-0.4.0.dist-info/WHEEL
erdb-0.4.0.dist-info/METADATA
erdb-0.4.0.dist-info/RECORD
