Metadata-Version: 2.1
Name: erdb
Version: 0.4.0
Summary: parse ELDEN RING files into JSON
Author-email: Filip Tomaszewski <phil25@pm.me>
Requires-Python: >=3.11
Classifier: License :: OSI Approved :: MIT License
Classifier: Programming Language :: Python :: 3
Classifier: Programming Language :: Python :: 3 :: Only
Classifier: Programming Language :: Python :: 3.11
Requires-Dist: Pillow >= 9.2
Requires-Dist: deepdiff >= 6.2
Requires-Dist: requests >= 2.28
Requires-Dist: fastapi >= 0.87
Requires-Dist: fastapi-versioning >= 0.10
Requires-Dist: uvicorn >= 0.19
Requires-Dist: jinja2 >= 3.1.2
Requires-Dist: htmlmin >= 0.1.12
Requires-Dist: pytest >= 7.1 ; extra == "test"
Project-URL: Home, https://github.com/EldenRingDatabase/erdb
Provides-Extra: test
